[
  {
    "hash": "田舎fm",
    "latestId": "https://komatatsu.github.io/inaka-fm/episode/13"
  },
  {
    "hash": "LayerXNOW",
    "latestId": "a2182aa2-d870-462a-88ee-4d805e4ed377"
  },
  {
    "hash": "tcfm",
    "latestId": "https://turingcomplete.fm/31"
  },
  {
    "hash": "React_Podcast",
    "latestId": "990a9681-9752-44cf-8821-650f267b2b87"
  },
  {
    "hash": "Google_Cloud_Platform_Podcast",
    "latestId": "85f2749c-908f-4459-833b-4e7ef1b3f6b9"
  },
  {
    "hash": "exportfm",
    "latestId": "https://export.fm/035"
  },
  {
    "hash": "managementstudio",
    "latestId": "8d9c3122-57dc-4a34-b5f8-ffedfcd4cd38"
  },
  {
    "hash": "新聞1面じゃなくても大事なこと",
    "latestId": "cf0505ad-8712-40b0-a170-b330006b010d"
  },
  {
    "hash": "ねじまきラジオ",
    "latestId": "https://nejimaki-radio.com/?p=7949"
  },
  {
    "hash": "乃木坂46のイイトコ",
    "latestId": "2429438a-b232-4cef-be5c-2bf0c7f71d97"
  },
  {
    "hash": "もう一度読むSRE",
    "latestId": "e6bd4bb9-981a-4727-aa00-77de1dad5512"
  },
  {
    "hash": "resizefm",
    "latestId": "e59258c9-fe3c-4803-8b8b-59b49a255e9d"
  },
  {
    "hash": "MEDIATALK",
    "latestId": "71ada135-ec98-4fcb-a3e8-b32d003618b5"
  },
  {
    "hash": "しがないラジオ",
    "latestId": "tag:soundcloud,2010:tracks/1139593186"
  },
  {
    "hash": "engineermeetingpodcast",
    "latestId": "tag:soundcloud,2010:tracks/1845922503"
  },
  {
    "hash": "strobofm",
    "latestId": "https://strobo.fm/episode/116/"
  },
  {
    "hash": "mosafm",
    "latestId": "https://mosa.fm/14"
  },
  {
    "hash": "mozaicfm",
    "latestId": "https://mozaic.fm/episodes/182/monthly-platform-202507.html"
  },
  {
    "hash": "狭浅",
    "latestId": "https://semaasa.net/?p=10253"
  },
  {
    "hash": "MOOKSTUDY日本の歴史",
    "latestId": "https://mookstudy1.mookmookradio.com/?p=2349"
  },
  {
    "hash": "ajitofm",
    "latestId": "https://ajito.fm/63/"
  },
  {
    "hash": "automagic",
    "latestId": "6745466e6c068300018888bc"
  },
  {
    "hash": "phpgenba",
    "latestId": "https://php-genba.shin1x1.com/49"
  },
  {
    "hash": "yatteikifm",
    "latestId": "https://yatteiki.fm/episode/62"
  },
  {
    "hash": "EMFM",
    "latestId": "a15b0732-b0d5-47f5-ba96-5976d1e6aaeb"
  },
  {
    "hash": "nextstepfm",
    "latestId": "tag:soundcloud,2010:tracks/2105430903"
  },
  {
    "hash": "前田ヒロ",
    "latestId": "https://hiromaeda.com/?p=1983"
  },
  {
    "hash": "未来授業",
    "latestId": "https://podcasts.tfm.co.jp/podcasts/tokyo/future/future2438_0330.mp3"
  },
  {
    "hash": "misreading",
    "latestId": "http://misreading.chat/?p=1248"
  },
  {
    "hash": "soussune",
    "latestId": "https://soussune.com/episode/44"
  },
  {
    "hash": "日本人の英語を変える！ポッドキャスト",
    "latestId": "3e5ec3e5-8383-4600-80a0-4d7d9879b1ea"
  },
  {
    "hash": "Peapod",
    "latestId": "Buzzsprout-15694671"
  },
  {
    "hash": "UIT_INSIDE",
    "latestId": "https://uit-inside.linecorp.com/episode/177"
  },
  {
    "hash": "ごりゅごcast",
    "latestId": "0fec7947-5b86-4c86-8af0-039b0d437509"
  },
  {
    "hash": "fukabori",
    "latestId": "gid://art19-episode-locator/V0/u_8RWrYPLanYbbOiPwfm_-34DOoTkXdIygKIkbi_lnQ"
  },
  {
    "hash": "ThePotluck",
    "latestId": "6fbc46f4-4269-4903-bbe3-a89b0ec0b77f"
  },
  {
    "hash": "テストラジオ",
    "latestId": "https://testradio.fm/?p=1683"
  },
  {
    "hash": "ドングリFM",
    "latestId": "894067a3-ae72-4ab9-826f-bc2fe2f01120"
  },
  {
    "hash": "くちをひらく",
    "latestId": "90a3c5cc-0fb1-40a6-b2d1-b33400aa334f"
  },
  {
    "hash": "はなれより",
    "latestId": "5e30f663-c2d3-4209-b0f8-d92623b36425"
  },
  {
    "hash": "スティレン",
    "latestId": "acd96ce3-e29f-4272-9769-fc1e9bda4dca"
  },
  {
    "hash": "researchatfm",
    "latestId": "https://researchat.fm/episode/170"
  },
  {
    "hash": "ノウカノタネ",
    "latestId": "9395588c-309d-4ba8-b6d8-20b21cde521d"
  },
  {
    "hash": "話し方のハナシ",
    "latestId": "https://hanashi.koelab.net/?p=6335"
  },
  {
    "hash": "フリーアジェンダ",
    "latestId": "3aa6a762-f9de-493a-8b2b-88751fd427f8"
  },
  {
    "hash": "yokohamanortham",
    "latestId": "5eff745a-0ae5-4acd-893a-eb6545fa107c"
  },
  {
    "hash": "SilverBulletClub",
    "latestId": "be3ae854-7841-429f-8adf-4977a591d698"
  },
  {
    "hash": "いんよう",
    "latestId": "4266a3d4-9450-45ba-8c53-b70b59c26e54"
  },
  {
    "hash": "AirSap",
    "latestId": "48fe15ae-1fee-47e9-928f-c83b56205bf3"
  },
  {
    "hash": "secure旅団",
    "latestId": "4fb3b2d6-f170-4dbf-a0ca-e9381681009b"
  },
  {
    "hash": "webrush",
    "latestId": "d1db1bb8-3d6a-4093-9f98-6f71898dd391"
  },
  {
    "hash": "OffTopic",
    "latestId": "0f7f85af-6932-4b95-a795-9471e384b7e1"
  },
  {
    "hash": "textafm",
    "latestId": "b842ef1f-9864-4461-8c05-254a68f61793"
  },
  {
    "hash": "jammingfm",
    "latestId": "fbe05441-75d7-4190-89ce-a9bfa03a01ca"
  },
  {
    "hash": "セキュリティのアレ",
    "latestId": "https://www.tsujileaks.com/?p=2061"
  },
  {
    "hash": "TodayILearned",
    "latestId": "4109e0ef-3cd7-4caa-88f3-80bc12720ef3"
  },
  {
    "hash": "パソコンサタデーナイト",
    "latestId": "03d8ff1d-b836-4937-9789-cf880e774687"
  },
  {
    "hash": "転職透明化ラジオ",
    "latestId": "5dc7d42b-0728-4c44-b477-662a4fc546fb"
  },
  {
    "hash": "hikifunefm",
    "latestId": "b72ff04c-af90-460d-a43e-8409be6d33a1"
  },
  {
    "hash": "omoiyarifm",
    "latestId": "https://omoiyarifm.github.io/episode/66"
  },
  {
    "hash": "研エンの仲",
    "latestId": "05bda586-4106-4d26-9d1b-7139ab2e840e"
  },
  {
    "hash": "ポッドキャストアワード観覧席",
    "latestId": "30a62567-ca8b-4d80-be03-62a35214ae44"
  },
  {
    "hash": "bgradio",
    "latestId": "9f7fd3c4-397a-48ff-bb76-75fce8ae33c0"
  },
  {
    "hash": "NeuroRadio",
    "latestId": "bdc8d3c8-b810-41bd-a998-5c27b266a8bc"
  },
  {
    "hash": "kyashfm",
    "latestId": "69a30d7b-5767-40b3-b586-a5d5d88e2cca"
  },
  {
    "hash": "たまデザFM",
    "latestId": "813c4cfb-9f70-4075-8519-dc5644166c59"
  },
  {
    "hash": "イシュミラジオ",
    "latestId": "isyumi.podbean.com/7cfd747e-3629-327b-a163-979a8ea7b834"
  },
  {
    "hash": "火曜日のおフロ",
    "latestId": "759d2241-a51e-4a39-a87a-a1316e6a302d"
  },
  {
    "hash": "basuke",
    "latestId": "df7f778e-554e-4161-884b-a0b58ffc2f57"
  },
  {
    "hash": "allstarsaas",
    "latestId": "19aa0b4c-9262-4ea5-90c3-301008a5d23f"
  },
  {
    "hash": "Wantedly_Engineering_Podcast",
    "latestId": "e87ca40b-b30d-4aa2-be64-04fa0ddeb964"
  },
  {
    "hash": "エンジニアと人生",
    "latestId": "gid://art19-episode-locator/V0/-QizXFzPUEziFw-QzTxji7Bddsqso0I_A2TZLoaIiHs"
  },
  {
    "hash": "超相対性理論",
    "latestId": "5d13d1fc-a887-4301-b97f-87217685c709"
  },
  {
    "hash": "よかった探し",
    "latestId": "2ac2e440-fc12-463d-80db-13b327e0cb44"
  },
  {
    "hash": "COTENRADIO",
    "latestId": "a08eb692-b8b4-4d5c-9b10-b6cc3df88a6f"
  },
  {
    "hash": "furoshiki_fm",
    "latestId": "753287ff-e417-4b23-8fa1-30a5c6e9c53a"
  },
  {
    "hash": "ひとくちPKI",
    "latestId": "61aa680c-6772-4691-a54f-39dc3126bed7"
  },
  {
    "hash": "一日三善",
    "latestId": "741d9bb7-9193-409b-b229-1d5123cf011d"
  },
  {
    "hash": "ゼロトピ",
    "latestId": "4036b266-dda1-4ed1-8a50-3784c5b69f09"
  },
  {
    "hash": "yurutech",
    "latestId": "db84a04d-234d-4c9f-85e4-90f6304d116b"
  },
  {
    "hash": "ほっとテック",
    "latestId": "1f1bdc62-5f02-4ef1-9c80-371c81c58e4d"
  },
  {
    "hash": "青T24時",
    "latestId": "45409fc3-610f-4b79-b1db-cadd07669ee9"
  },
  {
    "hash": "RepeatRhyme",
    "latestId": "5bc59e46-d17c-466a-a8d3-191edc4ea075"
  },
  {
    "hash": "ニュースの現場から",
    "latestId": "e02a01e3-c55f-4cc1-9fad-b3350029924e"
  },
  {
    "hash": "rebuildfm",
    "latestId": "https://rebuild.fm/411/"
  },
  {
    "hash": "メディアヌップ",
    "latestId": "18af25d4-7519-4cf2-b79c-724b05d43964"
  },
  {
    "hash": "arkbfm",
    "latestId": "fcd8ad1f-5b24-437c-b959-f225b40285f8"
  },
  {
    "hash": "やいやいラジオ",
    "latestId": "ff688969-3737-486b-a496-ef59ea0e4d8c"
  },
  {
    "hash": "ティーチャーティーチャー",
    "latestId": "6ae59214-3657-451a-a3d7-6254350af58e"
  },
  {
    "hash": "おいラジオ",
    "latestId": "79313fef-1583-445f-8b14-03b466673db8"
  },
  {
    "hash": "xcrossing",
    "latestId": "6757a76a-5acd-4985-bfe8-1374dd5cf682"
  },
  {
    "hash": "東京ポッド許可局",
    "latestId": "5e2a7674-7511-11f0-8881-e3fbe7e1394f"
  }
]