[
  {
    "hash": "tcfm",
    "latestId": "https://turingcomplete.fm/31"
  },
  {
    "hash": "MOOKSTUDY日本の歴史",
    "latestId": "https://mookstudy1.mookmookradio.com/?p=2349"
  },
  {
    "hash": "ThePotluck",
    "latestId": "11e86a16-2cbd-44f4-90da-cf91c44504c8"
  },
  {
    "hash": "secure旅団",
    "latestId": "e515b38c-aabc-422b-9b0c-945ceebea175"
  },
  {
    "hash": "研エンの仲",
    "latestId": "4ee36203-624a-433c-9140-5dc44a524951"
  },
  {
    "hash": "allstarsaas",
    "latestId": "692ce81c-b7c9-45bb-9f98-1538304e7c9d"
  },
  {
    "hash": "Wantedly_Engineering_Podcast",
    "latestId": "2d6d63f4-b467-41c6-9989-a1f27850d49d"
  },
  {
    "hash": "エンジニアと人生",
    "latestId": "gid://art19-episode-locator/V0/AQFk3-zYzSRgrhoM5W0ASkttuQ7D__W_LiIqef8NmYE"
  },
  {
    "hash": "よかった探し",
    "latestId": "7a516590-a471-4e62-9286-f3918fade238"
  },
  {
    "hash": "COTENRADIO",
    "latestId": "3d443aff-72f8-4642-8012-f96a8db82487"
  },
  {
    "hash": "メディアヌップ",
    "latestId": "837af723-2b08-47f5-9d6e-4b0e6a9aa3ad"
  },
  {
    "hash": "LayerXNOW",
    "latestId": "21048e22-c8ec-414a-b625-371de06c9f5a"
  },
  {
    "hash": "React_Podcast",
    "latestId": "990a9681-9752-44cf-8821-650f267b2b87"
  },
  {
    "hash": "Google_Cloud_Platform_Podcast",
    "latestId": "89c104fb-b277-4828-8586-4f19d24dfe9c"
  },
  {
    "hash": "exportfm",
    "latestId": "https://export.fm/033"
  },
  {
    "hash": "managementstudio",
    "latestId": "8d9c3122-57dc-4a34-b5f8-ffedfcd4cd38"
  },
  {
    "hash": "新聞1面じゃなくても大事なこと",
    "latestId": "2cc994e8-9d93-4b13-a45b-b08f0017d69c"
  },
  {
    "hash": "ねじまきラジオ",
    "latestId": "https://nejimaki-radio.com/?p=6414"
  },
  {
    "hash": "乃木坂46のイイトコ",
    "latestId": "fe8c55c7-f571-4ac5-9e13-e76b8be6b174"
  },
  {
    "hash": "もう一度読むSRE",
    "latestId": "b872ee80-f8d2-4a9b-a182-71121398c199"
  },
  {
    "hash": "resizefm",
    "latestId": "8d00dfba-c44e-4c34-84fc-6a9e4fce7203"
  },
  {
    "hash": "MEDIATALK",
    "latestId": "021befe6-8db0-4903-861b-b09000cde3d3"
  },
  {
    "hash": "バイリンガルニュース",
    "latestId": "e5938e4b-90a5-4a5e-ad19-a954c4e66635"
  },
  {
    "hash": "しがないラジオ",
    "latestId": "tag:soundcloud,2010:tracks/1139593186"
  },
  {
    "hash": "engineermeetingpodcast",
    "latestId": "tag:soundcloud,2010:tracks/1623903642"
  },
  {
    "hash": "strobofm",
    "latestId": "https://strobo.fm/episode/116/"
  },
  {
    "hash": "mosafm",
    "latestId": "https://mosa.fm/14"
  },
  {
    "hash": "mozaicfm",
    "latestId": "https://mozaic.fm/episodes/132/monthly-platform-202309.html"
  },
  {
    "hash": "狭浅",
    "latestId": "https://semaasa.net/?p=10089"
  },
  {
    "hash": "ajitofm",
    "latestId": "https://ajito.fm/63/"
  },
  {
    "hash": "automagic",
    "latestId": "6508843b3a09ae0001188928"
  },
  {
    "hash": "phpgenba",
    "latestId": "https://php-genba.shin1x1.com/48"
  },
  {
    "hash": "yatteikifm",
    "latestId": "https://yatteiki.fm/episode/62"
  },
  {
    "hash": "EMFM",
    "latestId": "ef3d5697-8fda-4ed7-8e85-8b8181c73189"
  },
  {
    "hash": "nextstepfm",
    "latestId": "tag:soundcloud,2010:tracks/1623433029"
  },
  {
    "hash": "前田ヒロ",
    "latestId": "https://hiromaeda.com/?p=1924"
  },
  {
    "hash": "未来授業",
    "latestId": "https://podcasts.tfm.co.jp/podcasts/tokyo/future/future2438_0330.mp3"
  },
  {
    "hash": "misreading",
    "latestId": "http://misreading.chat/?p=984"
  },
  {
    "hash": "soussune",
    "latestId": "https://soussune.com/episode/44"
  },
  {
    "hash": "jinseifm",
    "latestId": "https://kirimin.github.io/jinseifm/episode/15"
  },
  {
    "hash": "田舎fm",
    "latestId": "https://komatatsu.github.io/inaka-fm/episode/13"
  },
  {
    "hash": "日本人の英語を変える！ポッドキャスト",
    "latestId": "fe0d724b-952b-4e58-9fa0-453cae330c67"
  },
  {
    "hash": "Peapod",
    "latestId": "Buzzsprout-4408742"
  },
  {
    "hash": "UIT_INSIDE",
    "latestId": "https://uit-inside.linecorp.com/episode/148"
  },
  {
    "hash": "ごりゅごcast",
    "latestId": "1976ef7f-0aec-4997-8db5-855f35caaea2"
  },
  {
    "hash": "fukabori",
    "latestId": "gid://art19-episode-locator/V0/7BSmWL0S8188fwxuGnw2JkGgUHgOH3wss5IVVsdbOlc"
  },
  {
    "hash": "テストラジオ",
    "latestId": "https://testradio.fm/?p=1462"
  },
  {
    "hash": "ドングリFM",
    "latestId": "f470b95c-5fe8-4fa7-bf58-680c283a2ff6"
  },
  {
    "hash": "くちをひらく",
    "latestId": "00e37b41-c971-46c9-bc5b-b08e00e1e491"
  },
  {
    "hash": "はなれより",
    "latestId": "5e30f663-c2d3-4209-b0f8-d92623b36425"
  },
  {
    "hash": "スティレン",
    "latestId": "b612bb8b-bd93-4cb5-977c-a359c4ad91c1"
  },
  {
    "hash": "researchatfm",
    "latestId": "https://researchat.fm/episode/165"
  },
  {
    "hash": "ノウカノタネ",
    "latestId": "0c4d5996-2a5f-402a-babf-097877ab9cd6"
  },
  {
    "hash": "話し方のハナシ",
    "latestId": "https://hanashi.koelab.net/?p=3761"
  },
  {
    "hash": "フリーアジェンダ",
    "latestId": "63dc9113-90ea-4b41-b9d8-1bb0f0deb5dd"
  },
  {
    "hash": "yokohamanortham",
    "latestId": "00b58c5e-fc48-446e-a2e1-66e36f47723b"
  },
  {
    "hash": "SilverBulletClub",
    "latestId": "be3ae854-7841-429f-8adf-4977a591d698"
  },
  {
    "hash": "いんよう",
    "latestId": "10c03fc9-c3b9-42db-9b6c-7e1a0024ddc9"
  },
  {
    "hash": "AirSap",
    "latestId": "podlove-2023-09-09t21:12:34+00:00-bdab97036108c19"
  },
  {
    "hash": "webrush",
    "latestId": "b373e5ed-d7ba-47b7-afed-e6825ab276cf"
  },
  {
    "hash": "OffTopic",
    "latestId": "c2a635c5-8fe7-4ad7-8fb1-f648c3688226"
  },
  {
    "hash": "textafm",
    "latestId": "b842ef1f-9864-4461-8c05-254a68f61793"
  },
  {
    "hash": "jammingfm",
    "latestId": "00e74a5a-1dd7-4460-93bd-653a0141145d"
  },
  {
    "hash": "セキュリティのアレ",
    "latestId": "https://www.tsujileaks.com/?p=1610"
  },
  {
    "hash": "TodayILearned",
    "latestId": "7adb0e09-0233-46ea-83cc-f2f73f42f854"
  },
  {
    "hash": "パソコンサタデーナイト",
    "latestId": "03d8ff1d-b836-4937-9789-cf880e774687"
  },
  {
    "hash": "転職透明化ラジオ",
    "latestId": "5dc7d42b-0728-4c44-b477-662a4fc546fb"
  },
  {
    "hash": "hikifunefm",
    "latestId": "b72ff04c-af90-460d-a43e-8409be6d33a1"
  },
  {
    "hash": "omoiyarifm",
    "latestId": "https://omoiyarifm.github.io/episode/66"
  },
  {
    "hash": "ポッドキャストアワード観覧席",
    "latestId": "30a62567-ca8b-4d80-be03-62a35214ae44"
  },
  {
    "hash": "bgradio",
    "latestId": "9f7fd3c4-397a-48ff-bb76-75fce8ae33c0"
  },
  {
    "hash": "NeuroRadio",
    "latestId": "59237f25-7352-4402-8053-c5483b9e1d18"
  },
  {
    "hash": "kyashfm",
    "latestId": "77c886fb-d5cd-4bc7-add2-6dc92a5915f4"
  },
  {
    "hash": "submitslife",
    "latestId": "https://www.submits.life/episode/23"
  },
  {
    "hash": "たまデザFM",
    "latestId": "500b23c5-15aa-4076-8d69-524089224209"
  },
  {
    "hash": "イシュミラジオ",
    "latestId": "isyumi.podbean.com/7cfd747e-3629-327b-a163-979a8ea7b834"
  },
  {
    "hash": "火曜日のおフロ",
    "latestId": "7ca32b4c-5273-42f9-8468-c3763067e764"
  },
  {
    "hash": "basuke",
    "latestId": "df7f778e-554e-4161-884b-a0b58ffc2f57"
  },
  {
    "hash": "超相対性理論",
    "latestId": "a0ddf667-8758-4cd8-9efa-208aaa7aad44"
  },
  {
    "hash": "furoshiki_fm",
    "latestId": "bfd352b5-5184-419b-9645-208cc99b9ac8"
  },
  {
    "hash": "ひとくちPKI",
    "latestId": "c8bf3a1e-7339-42ce-8b29-adda910b9ff4"
  },
  {
    "hash": "一日三善",
    "latestId": "77f9e2fc-3003-4743-8629-b87dc9cabd23"
  },
  {
    "hash": "ゼロトピ",
    "latestId": "cce708b8-2e9c-4f2d-8aa2-20f9157eb7c5"
  },
  {
    "hash": "yurutech",
    "latestId": "2e520640-d8b8-4db8-ac28-9816342565f1"
  },
  {
    "hash": "ほっとテック",
    "latestId": "21559510-ad98-419d-ab02-8d77d06c9b37"
  },
  {
    "hash": "青T24時",
    "latestId": "eb2923f3-cc22-4834-a6c0-0edec70eb78b"
  },
  {
    "hash": "RepeatRhyme",
    "latestId": "8ae636c9-a23b-4aa9-b090-1cb816dbd554"
  },
  {
    "hash": "ニュースの現場から",
    "latestId": "f21efaec-d109-4ce6-8bf4-b082002ad83d"
  },
  {
    "hash": "rebuildfm",
    "latestId": "https://rebuild.fm/370/"
  },
  {
    "hash": "arkbfm",
    "latestId": "9faebee2-2107-40f6-aed5-db69661b301b"
  }
]